strome/__init__.py
strome/__version__.py
strome/cache.py
strome/const.py
strome/core.py
strome/error.py
strome/pipeline.py
strome/utils.py
strome/validate.py
strome/processors/__init__.py
strome/processors/jinja2.py
strome-1.0.0.dist-info/METADATA
strome-1.0.0.dist-info/WHEEL
strome-1.0.0.dist-info/top_level.txt
strome-1.0.0.dist-info/RECORD
