Metadata-Version: 2.1
Name: strome
Version: 1.0.0
Summary: Strome - Micro-framework for Python for building processing pipelines
Home-page: https://github.com/corvis/strome
Author: Dmitry Berezovsky
License: MIT
Keywords: pre-process processing pipiline
Platform: UNKNOWN
Classifier: Development Status :: 3 - Alpha
Classifier: Intended Audience :: Developers
Classifier: Topic :: Software Development :: Libraries :: Python Modules
Classifier: Topic :: Home Automation
Classifier: License :: OSI Approved :: MIT License
Classifier: Programming Language :: Python :: 3
Classifier: Programming Language :: Python :: 3.6
Classifier: Programming Language :: Python :: 3.7
Classifier: Programming Language :: Python :: 3.8
Classifier: Programming Language :: Python :: 3.9
Requires-Python: >3.6
Requires-Dist: cli-rack[validation] (~=1.0.1)
Requires-Dist: pyyaml (>=5.0.0)
Requires-Dist: jinja2 (>=3.0.0)
